xlsxdatagrid/__about__.py
xlsxdatagrid/__init__.py
xlsxdatagrid/colours.py
xlsxdatagrid/models.py
xlsxdatagrid/read.py
xlsxdatagrid/write.py
xlsxdatagrid/xlsxdatagrid.py
xlsxdatagrid/demo_schemas/__init__.py
xlsxdatagrid/demo_schemas/dtypes.py
xlsxdatagrid-0.3.4.dist-info/METADATA
xlsxdatagrid-0.3.4.dist-info/WHEEL
xlsxdatagrid-0.3.4.dist-info/licenses/LICENSE.txt
xlsxdatagrid-0.3.4.dist-info/RECORD
