Metadata-Version: 2.4
Name: xlsxdatagrid
Version: 0.3.4
Project-URL: Documentation, https://github.com/maxfordham/xlsxdatagrid#readme
Project-URL: Issues, https://github.com/maxfordham/xlsxdatagrid/issues
Project-URL: Source, https://github.com/maxfordham/xlsxdatagrid
Author-email: jgunstone <j.gunstone@maxfordham.com>
License-Expression: MIT
License-File: LICENSE.txt
Classifier: Development Status :: 4 - Beta
Classifier: Programming Language :: Python
Classifier: Programming Language :: Python :: 3.8
Classifier: Programming Language :: Python :: 3.9
Classifier: Programming Language :: Python :: 3.10
Classifier: Programming Language :: Python :: 3.11
Classifier: Programming Language :: Python :: 3.12
Classifier: Programming Language :: Python :: Implementation :: CPython
Classifier: Programming Language :: Python :: Implementation :: PyPy
Requires-Python: >=3.8
Requires-Dist: casefy
Requires-Dist: datamodel-code-generator>=0.28.5
Requires-Dist: dirty-equals
Requires-Dist: frictionless
Requires-Dist: frictionless[pandas]
Requires-Dist: jsonref
Requires-Dist: palettable
Requires-Dist: pydantic-extra-types
Requires-Dist: pydantic>2
Requires-Dist: python-calamine
Requires-Dist: xlsxwriter>=3.2.1
